inkrement/__init__.py
inkrement-0.0.1.dist-info/METADATA
inkrement-0.0.1.dist-info/RECORD
inkrement-0.0.1.dist-info/WHEEL
inkrement-0.0.1.dist-info/top_level.txt
